datection/__init__.py
datection/coherency.py
datection/cohesion.py
datection/context.py
datection/convert.py
datection/dtfuture.py
datection/elect.py
datection/exclude.py
datection/export.py
datection/lang.py
datection/models.py
datection/pack.py
datection/parse.py
datection/render.py
datection/schedule.py
datection/similarity.py
datection/timepoint.py
datection/timezone.py
datection/tokenize.py
datection/utils.py
datection/year_inheritance.py
datection/combine/__init__.py
datection/combine/common.py
datection/combine/count.py
datection/combine/remove.py
datection/combine/split.py
datection/data/__init__.py
datection/data/de.py
datection/data/en.py
datection/data/es.py
datection/data/fr.py
datection/data/it.py
datection/data/nl.py
datection/data/pt.py
datection/data/ru.py
datection/grammar/__init__.py
datection/grammar/en.py
datection/grammar/fr.py
datection/grammar/grammar_factory.py
datection/rendering/__init__.py
datection/rendering/base.py
datection/rendering/date.py
datection/rendering/date_time.py
datection/rendering/exceptions.py
datection/rendering/exclusion.py
datection/rendering/full.py
datection/rendering/long.py
datection/rendering/next_occurence.py
datection/rendering/place_summary.py
datection/rendering/seo.py
datection/rendering/time.py
datection/rendering/utils.py
datection/rendering/weekday_reccurence.py
datection/rendering/wrappers.py
datection/test/__init__.py
datection/test/test_coherency.py
datection/test/test_cohesion.py
datection/test/test_context.py
datection/test/test_convert.py
datection/test/test_count.py
datection/test/test_display.py
datection/test/test_elect.py
datection/test/test_export.py
datection/test/test_future.py
datection/test/test_grammar.py
datection/test/test_lang.py
datection/test/test_models.py
datection/test/test_pack.py
datection/test/test_parse.py
datection/test/test_remove.py
datection/test/test_render.py
datection/test/test_schedule.py
datection/test/test_similarity.py
datection/test/test_split.py
datection-4.0.7.dist-info/LICENSE
datection-4.0.7.dist-info/METADATA
datection-4.0.7.dist-info/WHEEL
datection-4.0.7.dist-info/top_level.txt
datection-4.0.7.dist-info/RECORD
