Metadata-Version: 2.1
Name: datection
Version: 4.0.7
Summary: Parse strings and extract normalized temporal data.
Home-page: https://github.com/mapado/datection
Author: Balthazar Rouberol
Maintainer: Julien Deniau
Maintainer-email: julien.deniau@mapado.com
License: MIT
Classifier: Intended Audience :: Developers
Classifier: License :: OSI Approved :: MIT License
Classifier: Programming Language :: Python
Classifier: Programming Language :: Python :: 3.5
Classifier: Programming Language :: Python :: 3.6
Classifier: Programming Language :: Python :: 3.7
Classifier: Programming Language :: Python :: 3.8
Classifier: Programming Language :: Python :: 3.9
Classifier: Programming Language :: Python :: 3.10
Classifier: Programming Language :: Python :: 3.11
Classifier: Programming Language :: Python :: 3.12
Requires-Python: >=3.5
License-File: LICENSE
Requires-Dist: python-dateutil
Requires-Dist: pyparsing (==2.0.3)
Requires-Dist: future
